dhti_elixir_base/__init__.py
dhti_elixir_base/agent.py
dhti_elixir_base/chain.py
dhti_elixir_base/chatllm.py
dhti_elixir_base/embedding.py
dhti_elixir_base/graph.py
dhti_elixir_base/llm.py
dhti_elixir_base/mcp.py
dhti_elixir_base/model.py
dhti_elixir_base/mydi.py
dhti_elixir_base/parlant_agent.py
dhti_elixir_base/server.py
dhti_elixir_base/space.py
dhti_elixir_base/cds_hook/__init__.py
dhti_elixir_base/cds_hook/card.py
dhti_elixir_base/cds_hook/generate_cards.py
dhti_elixir_base/cds_hook/request.py
dhti_elixir_base/cds_hook/request_parser.py
dhti_elixir_base/cds_hook/routes.py
dhti_elixir_base/cds_hook/service.py
dhti_elixir_base/fhir/__init__.py
dhti_elixir_base/fhir/fhir_search.py
dhti_elixir_base/fhir/smart_on_fhir.py
dhti_elixir_base/rag/__init__.py
dhti_elixir_base/rag/process.py
dhti_elixir_base/rag/redis_schema.yaml
dhti_elixir_base-1.4.1.dist-info/METADATA
dhti_elixir_base-1.4.1.dist-info/WHEEL
dhti_elixir_base-1.4.1.dist-info/licenses/AUTHORS.md
dhti_elixir_base-1.4.1.dist-info/licenses/LICENSE
dhti_elixir_base-1.4.1.dist-info/RECORD
