Metadata-Version: 2.4
Name: dhti-elixir-base
Version: 1.4.1
Summary: DHTI Elixir Base
Project-URL: Documentation, https://github.com/dermatologist/dhti
Project-URL: Homepage, https://nuchange.ca
Project-URL: Repository, https://github.com/dermatologist/dhti-elixir-base
Author-email: Bell Eapen <github_public@gulfdoctor.net>
License-Expression: MPL-2.0
License-File: AUTHORS.md
License-File: LICENSE
Keywords: Gen AI,dhti,python
Classifier: Development Status :: 4 - Beta
Classifier: Intended Audience :: Developers
Classifier: Intended Audience :: Healthcare Industry
Classifier: Operating System :: OS Independent
Classifier: Programming Language :: Python
Classifier: Programming Language :: Python :: 3
Classifier: Programming Language :: Python :: 3.11
Classifier: Programming Language :: Python :: 3.12
Classifier: Topic :: Scientific/Engineering :: Artificial Intelligence
Classifier: Topic :: Scientific/Engineering :: Information Analysis
Classifier: Topic :: Scientific/Engineering :: Medical Science Apps.
Classifier: Topic :: Software Development :: Libraries :: Python Modules
Requires-Python: <4.0,>=3.10
Requires-Dist: agency
Requires-Dist: fastapi
Requires-Dist: fhirclient
Requires-Dist: fhirpathpy
Requires-Dist: fhiry
Requires-Dist: httpx
Requires-Dist: kink
Requires-Dist: langchain-community
Requires-Dist: langchain-core
Requires-Dist: langchain-mcp-adapters
Requires-Dist: langchain<1.1.0,>=1.0.0
Requires-Dist: langgraph
Requires-Dist: langserve
Requires-Dist: mcp
Requires-Dist: parlant<4.0.0,>=3.0.0
Requires-Dist: pdfminer-six
Requires-Dist: python-dotenv
